configs/__init__.py
configs/antibiotics.json
configs/antibiotics_ampicillin.json
configs/antibiotics_tetracycline.json
configs/cell_wall.json
configs/cell_wall_test_rig.json
configs/cloud.json
configs/default.json
configs/generate_save_states.json
configs/gha_pytest.json
configs/lysis.json
configs/lysis_initiation.json
configs/lysis_trigger.json
configs/metabolism_redux.json
configs/metabolism_redux_classic.json
configs/reduced_murein.json
configs/run_parca.json
configs/shape.json
configs/spatial.json
configs/test_installation.json
configs/test_sherlock.json
configs/test_variant.json
configs/two_generations.json
configs/templates/analysis_standalone.json
configs/templates/create_variants_standalone.json
configs/templates/parca_standalone.json
configs/test_configs/cell_wall_division.json
configs/test_configs/test_add_process.json
configs/test_configs/test_blame.json
configs/test_configs/test_exclude_process.json
configs/test_configs/test_initial_state_overrides.json
configs/test_configs/test_load_state.json
configs/test_configs/test_lysis_initiation.json
configs/test_configs/test_save_state.json
ecoli/__init__.py
ecoli/py.typed
ecoli/analysis/__init__.py
ecoli/analysis/antibiotics_colony/__init__.py
ecoli/analysis/antibiotics_colony/amp_plots.py
ecoli/analysis/antibiotics_colony/exploration.py
ecoli/analysis/antibiotics_colony/load_data.py
ecoli/analysis/antibiotics_colony/metrics.py
ecoli/analysis/antibiotics_colony/plot.py
ecoli/analysis/antibiotics_colony/plot_utils.py
ecoli/analysis/antibiotics_colony/snapshot_and_hist_plot.py
ecoli/analysis/antibiotics_colony/spatial_correlation.py
ecoli/analysis/antibiotics_colony/tet_dry_mass.py
ecoli/analysis/antibiotics_colony/timeseries.py
ecoli/analysis/antibiotics_colony/validation.py
ecoli/analysis/antibiotics_colony/subgen_gene_plots/count_subgen.py
ecoli/analysis/antibiotics_colony/subgen_gene_plots/make_fig_1b.py
ecoli/analysis/causality_network/__init__.py
ecoli/analysis/causality_network/buildCausalityNetwork.py
vecoli-1.1.2.post1.dist-info/licenses/LICENSE
vecoli-1.1.2.post1.dist-info/METADATA
vecoli-1.1.2.post1.dist-info/WHEEL
vecoli-1.1.2.post1.dist-info/top_level.txt
vecoli-1.1.2.post1.dist-info/RECORD
