Metadata-Version: 2.4
Name: vEcoli
Version: 1.1.2.post1
Summary: Whole Cell E. coli Model
Requires-Python: ==3.12.9
License-File: LICENSE
Requires-Dist: numpy
Requires-Dist: scipy
Requires-Dist: biopython
Requires-Dist: cvxpy
Requires-Dist: cython
Requires-Dist: dill
Requires-Dist: duckdb
Requires-Dist: gcsfs
Requires-Dist: pyarrow
Requires-Dist: ipdb
Requires-Dist: ipython
Requires-Dist: line-profiler
Requires-Dist: altair
Requires-Dist: numba
Requires-Dist: orjson
Requires-Dist: ortools<9.11
Requires-Dist: pandas
Requires-Dist: polars
Requires-Dist: pymunk
Requires-Dist: scikit-image
Requires-Dist: scikit-learn
Requires-Dist: seaborn
Requires-Dist: swiglpk
Requires-Dist: sympy
Requires-Dist: tqdm
Requires-Dist: unum
Requires-Dist: vivarium-core
Requires-Dist: imageio[ffmpeg]
Requires-Dist: statsmodels
Requires-Dist: ecos
Requires-Dist: matplotlib
Requires-Dist: iteround
Requires-Dist: stochastic-arrow
Requires-Dist: autograd
Requires-Dist: xmltodict
Requires-Dist: vl-convert-python
Provides-Extra: dev
Requires-Dist: pytest; extra == "dev"
Requires-Dist: pytest-cov; extra == "dev"
Requires-Dist: mypy; extra == "dev"
Requires-Dist: ruff; extra == "dev"
Requires-Dist: pre-commit; extra == "dev"
Requires-Dist: jupyter; extra == "dev"
Requires-Dist: marimo[lsp,sql]; extra == "dev"
Provides-Extra: docs
Requires-Dist: Sphinx; extra == "docs"
Requires-Dist: sphinx-rtd-theme; extra == "docs"
Requires-Dist: nbsphinx; extra == "docs"
Dynamic: license-file
